extend_ai/__init__.py
extend_ai/batch_processor_run/__init__.py
extend_ai/batch_processor_run/client.py
extend_ai/batch_processor_run/raw_client.py
extend_ai/batch_processor_run/types/__init__.py
extend_ai/batch_processor_run/types/batch_processor_run_get_response.py
extend_ai/batch_workflow_run/__init__.py
extend_ai/batch_workflow_run/client.py
extend_ai/batch_workflow_run/raw_client.py
extend_ai/batch_workflow_run/types/__init__.py
extend_ai/batch_workflow_run/types/batch_workflow_run_create_request_inputs_item.py
extend_ai/batch_workflow_run/types/batch_workflow_run_create_response.py
extend_ai/client.py
extend_ai/core/__init__.py
extend_ai/core/api_error.py
extend_ai/core/client_wrapper.py
extend_ai/core/datetime_utils.py
extend_ai/core/file.py
extend_ai/core/force_multipart.py
extend_ai/core/http_client.py
extend_ai/core/http_response.py
extend_ai/core/jsonable_encoder.py
extend_ai/core/pydantic_utilities.py
extend_ai/core/query_encoder.py
extend_ai/core/remove_none_from_dict.py
extend_ai/core/request_options.py
extend_ai/core/serialization.py
extend_ai/core/unchecked_base_model.py
extend_ai/environment.py
extend_ai/errors/__init__.py
extend_ai/errors/bad_request_error.py
extend_ai/errors/not_found_error.py
extend_ai/errors/unauthorized_error.py
extend_ai/errors/unprocessable_entity_error.py
extend_ai/evaluation_set/__init__.py
extend_ai/evaluation_set/client.py
extend_ai/evaluation_set/raw_client.py
extend_ai/evaluation_set/types/__init__.py
extend_ai/evaluation_set/types/evaluation_set_create_response.py
extend_ai/evaluation_set_item/__init__.py
extend_ai/evaluation_set_item/client.py
extend_ai/evaluation_set_item/raw_client.py
extend_ai/evaluation_set_item/types/__init__.py
extend_ai/evaluation_set_item/types/evaluation_set_item_create_batch_request_items_item.py
extend_ai/evaluation_set_item/types/evaluation_set_item_create_batch_response.py
extend_ai/evaluation_set_item/types/evaluation_set_item_create_response.py
extend_ai-0.0.40.dist-info/METADATA
extend_ai-0.0.40.dist-info/WHEEL
extend_ai-0.0.40.dist-info/RECORD
